[
  {
    "company": "Wiza, Lakin and Kemmer",
    "position": "Design Engineer",
    "jobLocation": "San José Poaquil",
    "jobType": "internship",
    "status": "pending",
    "createdBy": "636abc924443cb11cfae1905",
    "createdAt": "2020-10-11T22:56:26Z"
  },
  {
    "company": "Toy-Pagac",
    "position": "Nuclear Power Engineer",
    "jobLocation": "Mörön",
    "jobType": "full-time",
    "status": "interview",
    "createdBy": "636abc924443cb11cfae1905",
    "createdAt": "2021-03-06T00:58:02Z"
  },
  {
    "company": "Beatty LLC",
    "position": "Professor",
    "jobLocation": "Lesnoy",
    "jobType": "internship",
    "status": "declined",
    "createdBy": "636abc924443cb11cfae1905",
    "createdAt": "2021-02-22T09:08:08Z"
  },
  {
    "company": "Bruen-Prohaska",
    "position": "Research Nurse",
    "jobLocation": "San Pedro",
    "jobType": "full-time",
    "status": "declined",
    "createdBy": "636abc924443cb11cfae1905",
    "createdAt": "2022-03-20T04:57:50Z"
  },
  {
    "company": "Boehm-Feest",
    "position": "Teacher",
    "jobLocation": "Nuevo Arraiján",
    "jobType": "part-time",
    "status": "declined",
    "createdBy": "636abc924443cb11cfae1905",
    "createdAt": "2020-03-09T22:15:54Z"
  },
  {
    "company": "Leffler-Howell",
    "position": "Biostatistician IV",
    "jobLocation": "P’asanauri",
    "jobType": "remote",
    "status": "interview",
    "createdBy": "636abc924443cb11cfae1905",
    "createdAt": "2020-05-19T04:28:44Z"
  },
  {
    "company": "Schuster and Sons",
    "position": "Compensation Analyst",
    "jobLocation": "Lukou",
    "jobType": "part-time",
    "status": "declined",
    "createdBy": "636abc924443cb11cfae1905",
    "createdAt": "2022-05-31T13:53:34Z"
  },
  {
    "company": "Wolff-Kertzmann",
    "position": "Technical Writer",
    "jobLocation": "Alta Gracia",
    "jobType": "part-time",
    "status": "declined",
    "createdBy": "636abc924443cb11cfae1905",
    "createdAt": "2020-02-01T22:44:32Z"
  },
  {
    "company": "Monahan, Cormier and Muller",
    "position": "Business Systems Development Analyst",
    "jobLocation": "Hongwŏn",
    "jobType": "part-time",
    "status": "interview",
    "createdBy": "636abc924443cb11cfae1905",
    "createdAt": "2021-09-29T00:36:57Z"
  },
  {
    "company": "Lind, Reilly and Frami",
    "position": "Business Systems Development Analyst",
    "jobLocation": "Lélouma",
    "jobType": "full-time",
    "status": "declined",
    "createdBy": "636abc924443cb11cfae1905",
    "createdAt": "2021-10-24T20:40:49Z"
  },
  {
    "company": "Oberbrunner, Herzog and Krajcik",
    "position": "Internal Auditor",
    "jobLocation": "Consolacion",
    "jobType": "part-time",
    "status": "pending",
    "createdBy": "636abc924443cb11cfae1905",
    "createdAt": "2022-05-29T09:44:29Z"
  },
  {
    "company": "Ledner-Goodwin",
    "position": "Chemical Engineer",
    "jobLocation": "Lugang",
    "jobType": "internship",
    "status": "declined",
    "createdBy": "636abc924443cb11cfae1905",
    "createdAt": "2021-02-10T01:12:22Z"
  },
  {
    "company": "Sauer-Mueller",
    "position": "Operator",
    "jobLocation": "Semënov",
    "jobType": "remote",
    "status": "declined",
    "createdBy": "636abc924443cb11cfae1905",
    "createdAt": "2021-12-02T01:03:29Z"
  },
  {
    "company": "Auer and Sons",
    "position": "Assistant Manager",
    "jobLocation": "Caramay",
    "jobType": "full-time",
    "status": "interview",
    "createdBy": "636abc924443cb11cfae1905",
    "createdAt": "2022-01-29T13:26:15Z"
  },
  {
    "company": "Cummings-Mueller",
    "position": "Administrative Assistant II",
    "jobLocation": "Roma",
    "jobType": "part-time",
    "status": "pending",
    "createdBy": "636abc924443cb11cfae1905",
    "createdAt": "2020-03-15T19:21:30Z"
  },
  {
    "company": "Leannon, Price and Cole",
    "position": "Product Engineer",
    "jobLocation": "Qianyou",
    "jobType": "remote",
    "status": "interview",
    "createdBy": "636abc924443cb11cfae1905",
    "createdAt": "2022-02-27T19:50:35Z"
  },
  {
    "company": "Dickens Group",
    "position": "Mechanical Systems Engineer",
    "jobLocation": "Victoria",
    "jobType": "internship",
    "status": "interview",
    "createdBy": "636abc924443cb11cfae1905",
    "createdAt": "2022-01-22T17:01:18Z"
  },
  {
    "company": "Thompson-O'Hara",
    "position": "Recruiting Manager",
    "jobLocation": "Karangnunggal",
    "jobType": "internship",
    "status": "interview",
    "createdBy": "636abc924443cb11cfae1905",
    "createdAt": "2020-11-10T09:00:18Z"
  },
  {
    "company": "Connelly and Sons",
    "position": "Associate Professor",
    "jobLocation": "Portoviejo",
    "jobType": "full-time",
    "status": "pending",
    "createdBy": "636abc924443cb11cfae1905",
    "createdAt": "2022-07-02T08:34:50Z"
  },
  {
    "company": "Keebler and Sons",
    "position": "Pharmacist",
    "jobLocation": "Pohang",
    "jobType": "internship",
    "status": "declined",
    "createdBy": "636abc924443cb11cfae1905",
    "createdAt": "2020-08-29T03:47:33Z"
  },
  {
    "company": "Blick-Feest",
    "position": "Operator",
    "jobLocation": "Kembangkerang Lauk Timur",
    "jobType": "remote",
    "status": "pending",
    "createdBy": "636abc924443cb11cfae1905",
    "createdAt": "2021-05-15T03:51:28Z"
  },
  {
    "company": "Leannon, McLaughlin and Kris",
    "position": "Environmental Tech",
    "jobLocation": "Rominimbang",
    "jobType": "full-time",
    "status": "pending",
    "createdBy": "636abc924443cb11cfae1905",
    "createdAt": "2021-11-09T00:21:24Z"
  },
  {
    "company": "Johnston Inc",
    "position": "Graphic Designer",
    "jobLocation": "Jemielno",
    "jobType": "remote",
    "status": "pending",
    "createdBy": "636abc924443cb11cfae1905",
    "createdAt": "2021-12-30T12:38:47Z"
  },
  {
    "company": "Homenick, Moore and Anderson",
    "position": "Analog Circuit Design manager",
    "jobLocation": "Az Zaytūnīyah",
    "jobType": "part-time",
    "status": "interview",
    "createdBy": "636abc924443cb11cfae1905",
    "createdAt": "2019-12-15T00:40:57Z"
  },
  {
    "company": "Mitchell Group",
    "position": "Analyst Programmer",
    "jobLocation": "Għaxaq",
    "jobType": "remote",
    "status": "declined",
    "createdBy": "636abc924443cb11cfae1905",
    "createdAt": "2020-08-04T07:45:11Z"
  },
  {
    "company": "Smith, Mann and Fisher",
    "position": "Mechanical Systems Engineer",
    "jobLocation": "Shimen",
    "jobType": "remote",
    "status": "pending",
    "createdBy": "636abc924443cb11cfae1905",
    "createdAt": "2021-11-03T21:05:07Z"
  },
  {
    "company": "Rippin LLC",
    "position": "Administrative Officer",
    "jobLocation": "Ulichnoye",
    "jobType": "full-time",
    "status": "interview",
    "createdBy": "636abc924443cb11cfae1905",
    "createdAt": "2020-08-24T23:45:38Z"
  },
  {
    "company": "Mills-Mitchell",
    "position": "Physical Therapy Assistant",
    "jobLocation": "Gombang",
    "jobType": "remote",
    "status": "pending",
    "createdBy": "636abc924443cb11cfae1905",
    "createdAt": "2019-12-13T05:03:50Z"
  },
  {
    "company": "Schowalter and Sons",
    "position": "Dental Hygienist",
    "jobLocation": "Manjakandriana",
    "jobType": "remote",
    "status": "declined",
    "createdBy": "636abc924443cb11cfae1905",
    "createdAt": "2019-12-27T15:49:29Z"
  },
  {
    "company": "Casper, Goldner and Okuneva",
    "position": "Account Executive",
    "jobLocation": "Long Xuyên",
    "jobType": "part-time",
    "status": "pending",
    "createdBy": "636abc924443cb11cfae1905",
    "createdAt": "2021-10-19T04:36:14Z"
  },
  {
    "company": "Tillman, Hegmann and Lakin",
    "position": "Nurse",
    "jobLocation": "Quchomo",
    "jobType": "remote",
    "status": "interview",
    "createdBy": "636abc924443cb11cfae1905",
    "createdAt": "2020-11-04T07:34:43Z"
  },
  {
    "company": "Towne, Gutmann and Wilderman",
    "position": "Programmer II",
    "jobLocation": "Jinan",
    "jobType": "remote",
    "status": "pending",
    "createdBy": "636abc924443cb11cfae1905",
    "createdAt": "2022-05-29T22:20:05Z"
  },
  {
    "company": "Doyle, Harvey and Boyer",
    "position": "Automation Specialist III",
    "jobLocation": "Estância Velha",
    "jobType": "remote",
    "status": "pending",
    "createdBy": "636abc924443cb11cfae1905",
    "createdAt": "2019-11-27T22:30:13Z"
  },
  {
    "company": "Douglas, Rodriguez and Hettinger",
    "position": "Account Executive",
    "jobLocation": "Mtubatuba",
    "jobType": "internship",
    "status": "declined",
    "createdBy": "636abc924443cb11cfae1905",
    "createdAt": "2020-10-16T07:52:24Z"
  },
  {
    "company": "Rau, Jenkins and Boyer",
    "position": "Librarian",
    "jobLocation": "Li’an",
    "jobType": "full-time",
    "status": "interview",
    "createdBy": "636abc924443cb11cfae1905",
    "createdAt": "2022-07-11T18:07:38Z"
  },
  {
    "company": "Ortiz-Romaguera",
    "position": "Product Engineer",
    "jobLocation": "Pingshan",
    "jobType": "internship",
    "status": "declined",
    "createdBy": "636abc924443cb11cfae1905",
    "createdAt": "2020-12-06T23:53:46Z"
  },
  {
    "company": "Thompson-Trantow",
    "position": "Operator",
    "jobLocation": "Turangi",
    "jobType": "full-time",
    "status": "pending",
    "createdBy": "636abc924443cb11cfae1905",
    "createdAt": "2019-10-02T05:29:22Z"
  },
  {
    "company": "Cassin, Kub and Bernier",
    "position": "Community Outreach Specialist",
    "jobLocation": "Narvacan",
    "jobType": "remote",
    "status": "declined",
    "createdBy": "636abc924443cb11cfae1905",
    "createdAt": "2020-11-16T23:12:32Z"
  },
  {
    "company": "Johnson-Gusikowski",
    "position": "General Manager",
    "jobLocation": "Sharīfābād",
    "jobType": "internship",
    "status": "interview",
    "createdBy": "636abc924443cb11cfae1905",
    "createdAt": "2022-03-08T11:32:33Z"
  },
  {
    "company": "Wolf and Sons",
    "position": "Senior Financial Analyst",
    "jobLocation": "Cool űrhajó",
    "jobType": "part-time",
    "status": "pending",
    "createdBy": "636abc924443cb11cfae1905",
    "createdAt": "2020-12-22T06:18:50Z"
  },
  {
    "company": "Gusikowski, Wyman and Gusikowski",
    "position": "Compensation Analyst",
    "jobLocation": "Obsza",
    "jobType": "internship",
    "status": "declined",
    "createdBy": "636abc924443cb11cfae1905",
    "createdAt": "2020-02-02T16:02:20Z"
  },
  {
    "company": "Maggio, Franecki and Schuster",
    "position": "Senior Cost Accountant",
    "jobLocation": "Sędziszów",
    "jobType": "part-time",
    "status": "interview",
    "createdBy": "636abc924443cb11cfae1905",
    "createdAt": "2021-07-24T09:11:34Z"
  },
  {
    "company": "Daugherty Group",
    "position": "Internal Auditor",
    "jobLocation": "Karangduren Dua",
    "jobType": "internship",
    "status": "declined",
    "createdBy": "636abc924443cb11cfae1905",
    "createdAt": "2022-01-31T18:15:41Z"
  },
  {
    "company": "Raynor-Breitenberg",
    "position": "Senior Cost Accountant",
    "jobLocation": "Foča",
    "jobType": "full-time",
    "status": "interview",
    "createdBy": "636abc924443cb11cfae1905",
    "createdAt": "2022-09-07T02:18:16Z"
  },
  {
    "company": "Harris, Blanda and Bednar",
    "position": "Research Assistant I",
    "jobLocation": "Imeni Babushkina",
    "jobType": "internship",
    "status": "pending",
    "createdBy": "636abc924443cb11cfae1905",
    "createdAt": "2020-12-30T09:28:29Z"
  },
  {
    "company": "Dooley-Hansen",
    "position": "Safety Technician IV",
    "jobLocation": "Sobreira",
    "jobType": "part-time",
    "status": "declined",
    "createdBy": "636abc924443cb11cfae1905",
    "createdAt": "2020-08-16T08:04:39Z"
  },
  {
    "company": "Greenfelder-Rohan",
    "position": "Executive Secretary",
    "jobLocation": "Spas-Zaulok",
    "jobType": "remote",
    "status": "declined",
    "createdBy": "636abc924443cb11cfae1905",
    "createdAt": "2021-01-02T17:50:48Z"
  },
  {
    "company": "Zboncak Group",
    "position": "Programmer I",
    "jobLocation": "Āshkhāneh",
    "jobType": "part-time",
    "status": "pending",
    "createdBy": "636abc924443cb11cfae1905",
    "createdAt": "2021-08-12T10:59:02Z"
  },
  {
    "company": "Mohr Group",
    "position": "VP Quality Control",
    "jobLocation": "Rudnya",
    "jobType": "part-time",
    "status": "pending",
    "createdBy": "636abc924443cb11cfae1905",
    "createdAt": "2020-04-15T04:44:29Z"
  },
  {
    "company": "Konopelski, McGlynn and Quitzon",
    "position": "Safety Technician II",
    "jobLocation": "Jianqiao",
    "jobType": "full-time",
    "status": "declined",
    "createdBy": "636abc924443cb11cfae1905",
    "createdAt": "2021-02-27T10:07:48Z"
  },
  {
    "company": "Witting LLC",
    "position": "Database Administrator III",
    "jobLocation": "Erími",
    "jobType": "internship",
    "status": "interview",
    "createdBy": "636abc924443cb11cfae1905",
    "createdAt": "2020-09-11T06:49:51Z"
  },
  {
    "company": "Batz, Wisoky and Batz",
    "position": "Editor",
    "jobLocation": "Santa Maria",
    "jobType": "remote",
    "status": "declined",
    "createdBy": "636abc924443cb11cfae1905",
    "createdAt": "2021-06-08T10:05:58Z"
  },
  {
    "company": "Oberbrunner Group",
    "position": "Actuary",
    "jobLocation": "Dahua",
    "jobType": "remote",
    "status": "interview",
    "createdBy": "636abc924443cb11cfae1905",
    "createdAt": "2022-06-22T12:32:14Z"
  },
  {
    "company": "Johns, Farrell and Mosciski",
    "position": "Accounting Assistant III",
    "jobLocation": "Peristerá",
    "jobType": "remote",
    "status": "pending",
    "createdBy": "636abc924443cb11cfae1905",
    "createdAt": "2020-02-24T10:11:10Z"
  },
  {
    "company": "Wolf, Wunsch and Rice",
    "position": "Media Manager III",
    "jobLocation": "Wasquehal",
    "jobType": "internship",
    "status": "pending",
    "createdBy": "636abc924443cb11cfae1905",
    "createdAt": "2020-08-09T14:11:13Z"
  },
  {
    "company": "Crona, Sanford and Bogan",
    "position": "Electrical Engineer",
    "jobLocation": "Syntul",
    "jobType": "remote",
    "status": "declined",
    "createdBy": "636abc924443cb11cfae1905",
    "createdAt": "2021-12-29T09:34:52Z"
  },
  {
    "company": "Metz-Jerde",
    "position": "Help Desk Operator",
    "jobLocation": "Suocheng",
    "jobType": "part-time",
    "status": "pending",
    "createdBy": "636abc924443cb11cfae1905",
    "createdAt": "2020-05-31T16:55:42Z"
  },
  {
    "company": "Tillman-Haley",
    "position": "Recruiter",
    "jobLocation": "Fort Worth",
    "jobType": "internship",
    "status": "interview",
    "createdBy": "636abc924443cb11cfae1905",
    "createdAt": "2022-02-04T20:28:23Z"
  },
  {
    "company": "Mohr LLC",
    "position": "Physical Therapy Assistant",
    "jobLocation": "Bilajari",
    "jobType": "internship",
    "status": "pending",
    "createdBy": "636abc924443cb11cfae1905",
    "createdAt": "2022-04-20T00:15:16Z"
  },
  {
    "company": "Turner-Lakin",
    "position": "Systems Administrator IV",
    "jobLocation": "Dili",
    "jobType": "full-time",
    "status": "interview",
    "createdBy": "636abc924443cb11cfae1905",
    "createdAt": "2021-08-15T09:16:50Z"
  },
  {
    "company": "Medhurst LLC",
    "position": "Pharmacist",
    "jobLocation": "Cigaluh",
    "jobType": "part-time",
    "status": "declined",
    "createdBy": "636abc924443cb11cfae1905",
    "createdAt": "2022-02-18T12:06:21Z"
  },
  {
    "company": "Schneider-White",
    "position": "Environmental Specialist",
    "jobLocation": "Veshnyaki",
    "jobType": "internship",
    "status": "declined",
    "createdBy": "636abc924443cb11cfae1905",
    "createdAt": "2022-02-03T16:43:19Z"
  },
  {
    "company": "Pacocha, Mayer and Gutmann",
    "position": "Teacher",
    "jobLocation": "Kozelets’",
    "jobType": "full-time",
    "status": "pending",
    "createdBy": "636abc924443cb11cfae1905",
    "createdAt": "2020-06-07T21:12:38Z"
  },
  {
    "company": "Haag-Weissnat",
    "position": "Food Chemist",
    "jobLocation": "Hedong",
    "jobType": "part-time",
    "status": "interview",
    "createdBy": "636abc924443cb11cfae1905",
    "createdAt": "2022-04-02T20:30:59Z"
  },
  {
    "company": "Dach-Gusikowski",
    "position": "Financial Advisor",
    "jobLocation": "Gryaznovskoye",
    "jobType": "full-time",
    "status": "interview",
    "createdBy": "636abc924443cb11cfae1905",
    "createdAt": "2022-06-23T01:27:45Z"
  },
  {
    "company": "Veum, Harber and Lubowitz",
    "position": "Account Representative III",
    "jobLocation": "Puerres",
    "jobType": "part-time",
    "status": "interview",
    "createdBy": "636abc924443cb11cfae1905",
    "createdAt": "2020-03-18T13:00:56Z"
  },
  {
    "company": "Erdman-Weber",
    "position": "Senior Quality Engineer",
    "jobLocation": "Kikinda",
    "jobType": "remote",
    "status": "pending",
    "createdBy": "636abc924443cb11cfae1905",
    "createdAt": "2021-01-06T20:59:24Z"
  },
  {
    "company": "Walter-Heathcote",
    "position": "Assistant Professor",
    "jobLocation": "Xinzhuang",
    "jobType": "internship",
    "status": "interview",
    "createdBy": "636abc924443cb11cfae1905",
    "createdAt": "2020-04-09T05:14:16Z"
  },
  {
    "company": "Monahan, Ledner and Labadie",
    "position": "Mechanical Systems Engineer",
    "jobLocation": "Bykov",
    "jobType": "internship",
    "status": "interview",
    "createdBy": "636abc924443cb11cfae1905",
    "createdAt": "2021-09-08T20:09:36Z"
  },
  {
    "company": "Mayer Inc",
    "position": "Geological Engineer",
    "jobLocation": "Kos",
    "jobType": "full-time",
    "status": "pending",
    "createdBy": "636abc924443cb11cfae1905",
    "createdAt": "2020-08-06T22:43:19Z"
  },
  {
    "company": "Harris LLC",
    "position": "Research Associate",
    "jobLocation": "Ōtsu-shi",
    "jobType": "part-time",
    "status": "declined",
    "createdBy": "636abc924443cb11cfae1905",
    "createdAt": "2020-12-11T23:43:18Z"
  },
  {
    "company": "Conn and Sons",
    "position": "General Manager",
    "jobLocation": "Hexing",
    "jobType": "full-time",
    "status": "pending",
    "createdBy": "636abc924443cb11cfae1905",
    "createdAt": "2021-06-23T21:18:31Z"
  },
  {
    "company": "Flatley, Bayer and Johnson",
    "position": "Quality Engineer",
    "jobLocation": "Lộc Bình",
    "jobType": "part-time",
    "status": "declined",
    "createdBy": "636abc924443cb11cfae1905",
    "createdAt": "2021-01-18T22:04:30Z"
  },
  {
    "company": "Carroll Inc",
    "position": "Marketing Manager",
    "jobLocation": "Bonn",
    "jobType": "full-time",
    "status": "interview",
    "createdBy": "636abc924443cb11cfae1905",
    "createdAt": "2019-12-14T11:44:03Z"
  },
  {
    "company": "Luettgen, Feest and Hegmann",
    "position": "VP Accounting",
    "jobLocation": "Atikokan",
    "jobType": "part-time",
    "status": "interview",
    "createdBy": "636abc924443cb11cfae1905",
    "createdAt": "2021-05-02T14:52:31Z"
  }
]
